{
  "bookId": "4",
  "testamentId": "1",
  "links": [
    {
      "href": "https://thiruvachanam.in/ShowStatementsOfChapter.do?c=120&b=4&t=1",
      "text": "ആമുഖം"
    },
    {
      "href": "https://thiruvachanam.in/ShowStatementsOfChapter.do?c=121&b=4&t=1",
      "text": "1"
    },
    {
      "href": "https://thiruvachanam.in/ShowStatementsOfChapter.do?c=122&b=4&t=1",
      "text": "2"
    },
    {
      "href": "https://thiruvachanam.in/ShowStatementsOfChapter.do?c=123&b=4&t=1",
      "text": "3"
    },
    {
      "href": "https://thiruvachanam.in/ShowStatementsOfChapter.do?c=124&b=4&t=1",
      "text": "4"
    },
    {
      "href": "https://thiruvachanam.in/ShowStatementsOfChapter.do?c=125&b=4&t=1",
      "text": "5"
    },
    {
      "href": "https://thiruvachanam.in/ShowStatementsOfChapter.do?c=126&b=4&t=1",
      "text": "6"
    },
    {
      "href": "https://thiruvachanam.in/ShowStatementsOfChapter.do?c=127&b=4&t=1",
      "text": "7"
    },
    {
      "href": "https://thiruvachanam.in/ShowStatementsOfChapter.do?c=128&b=4&t=1",
      "text": "8"
    },
    {
      "href": "https://thiruvachanam.in/ShowStatementsOfChapter.do?c=129&b=4&t=1",
      "text": "9"
    },
    {
      "href": "https://thiruvachanam.in/ShowStatementsOfChapter.do?c=130&b=4&t=1",
      "text": "10"
    },
    {
      "href": "https://thiruvachanam.in/ShowStatementsOfChapter.do?c=131&b=4&t=1",
      "text": "11"
    },
    {
      "href": "https://thiruvachanam.in/ShowStatementsOfChapter.do?c=132&b=4&t=1",
      "text": "12"
    },
    {
      "href": "https://thiruvachanam.in/ShowStatementsOfChapter.do?c=133&b=4&t=1",
      "text": "13"
    },
    {
      "href": "https://thiruvachanam.in/ShowStatementsOfChapter.do?c=134&b=4&t=1",
      "text": "14"
    },
    {
      "href": "https://thiruvachanam.in/ShowStatementsOfChapter.do?c=135&b=4&t=1",
      "text": "15"
    },
    {
      "href": "https://thiruvachanam.in/ShowStatementsOfChapter.do?c=136&b=4&t=1",
      "text": "16"
    },
    {
      "href": "https://thiruvachanam.in/ShowStatementsOfChapter.do?c=137&b=4&t=1",
      "text": "17"
    },
    {
      "href": "https://thiruvachanam.in/ShowStatementsOfChapter.do?c=138&b=4&t=1",
      "text": "18"
    },
    {
      "href": "https://thiruvachanam.in/ShowStatementsOfChapter.do?c=139&b=4&t=1",
      "text": "19"
    },
    {
      "href": "https://thiruvachanam.in/ShowStatementsOfChapter.do?c=140&b=4&t=1",
      "text": "20"
    },
    {
      "href": "https://thiruvachanam.in/ShowStatementsOfChapter.do?c=141&b=4&t=1",
      "text": "21"
    },
    {
      "href": "https://thiruvachanam.in/ShowStatementsOfChapter.do?c=142&b=4&t=1",
      "text": "22"
    },
    {
      "href": "https://thiruvachanam.in/ShowStatementsOfChapter.do?c=143&b=4&t=1",
      "text": "23"
    },
    {
      "href": "https://thiruvachanam.in/ShowStatementsOfChapter.do?c=144&b=4&t=1",
      "text": "24"
    },
    {
      "href": "https://thiruvachanam.in/ShowStatementsOfChapter.do?c=145&b=4&t=1",
      "text": "25"
    },
    {
      "href": "https://thiruvachanam.in/ShowStatementsOfChapter.do?c=146&b=4&t=1",
      "text": "26"
    },
    {
      "href": "https://thiruvachanam.in/ShowStatementsOfChapter.do?c=147&b=4&t=1",
      "text": "27"
    },
    {
      "href": "https://thiruvachanam.in/ShowStatementsOfChapter.do?c=148&b=4&t=1",
      "text": "28"
    },
    {
      "href": "https://thiruvachanam.in/ShowStatementsOfChapter.do?c=149&b=4&t=1",
      "text": "29"
    },
    {
      "href": "https://thiruvachanam.in/ShowStatementsOfChapter.do?c=150&b=4&t=1",
      "text": "30"
    },
    {
      "href": "https://thiruvachanam.in/ShowStatementsOfChapter.do?c=151&b=4&t=1",
      "text": "31"
    },
    {
      "href": "https://thiruvachanam.in/ShowStatementsOfChapter.do?c=152&b=4&t=1",
      "text": "32"
    },
    {
      "href": "https://thiruvachanam.in/ShowStatementsOfChapter.do?c=153&b=4&t=1",
      "text": "33"
    },
    {
      "href": "https://thiruvachanam.in/ShowStatementsOfChapter.do?c=154&b=4&t=1",
      "text": "34"
    },
    {
      "href": "https://thiruvachanam.in/ShowStatementsOfChapter.do?c=155&b=4&t=1",
      "text": "35"
    },
    {
      "href": "https://thiruvachanam.in/ShowStatementsOfChapter.do?c=156&b=4&t=1",
      "text": "36"
    }
  ]
}