{
  "bookId": "7",
  "testamentId": "1",
  "links": [
    {
      "href": "https://thiruvachanam.in/ShowStatementsOfChapter.do?c=217&b=7&t=1",
      "text": "ആമുഖം"
    },
    {
      "href": "https://thiruvachanam.in/ShowStatementsOfChapter.do?c=218&b=7&t=1",
      "text": "1"
    },
    {
      "href": "https://thiruvachanam.in/ShowStatementsOfChapter.do?c=219&b=7&t=1",
      "text": "2"
    },
    {
      "href": "https://thiruvachanam.in/ShowStatementsOfChapter.do?c=220&b=7&t=1",
      "text": "3"
    },
    {
      "href": "https://thiruvachanam.in/ShowStatementsOfChapter.do?c=221&b=7&t=1",
      "text": "4"
    },
    {
      "href": "https://thiruvachanam.in/ShowStatementsOfChapter.do?c=222&b=7&t=1",
      "text": "5"
    },
    {
      "href": "https://thiruvachanam.in/ShowStatementsOfChapter.do?c=223&b=7&t=1",
      "text": "6"
    },
    {
      "href": "https://thiruvachanam.in/ShowStatementsOfChapter.do?c=224&b=7&t=1",
      "text": "7"
    },
    {
      "href": "https://thiruvachanam.in/ShowStatementsOfChapter.do?c=225&b=7&t=1",
      "text": "8"
    },
    {
      "href": "https://thiruvachanam.in/ShowStatementsOfChapter.do?c=226&b=7&t=1",
      "text": "9"
    },
    {
      "href": "https://thiruvachanam.in/ShowStatementsOfChapter.do?c=227&b=7&t=1",
      "text": "10"
    },
    {
      "href": "https://thiruvachanam.in/ShowStatementsOfChapter.do?c=228&b=7&t=1",
      "text": "11"
    },
    {
      "href": "https://thiruvachanam.in/ShowStatementsOfChapter.do?c=229&b=7&t=1",
      "text": "12"
    },
    {
      "href": "https://thiruvachanam.in/ShowStatementsOfChapter.do?c=230&b=7&t=1",
      "text": "13"
    },
    {
      "href": "https://thiruvachanam.in/ShowStatementsOfChapter.do?c=231&b=7&t=1",
      "text": "14"
    },
    {
      "href": "https://thiruvachanam.in/ShowStatementsOfChapter.do?c=232&b=7&t=1",
      "text": "15"
    },
    {
      "href": "https://thiruvachanam.in/ShowStatementsOfChapter.do?c=233&b=7&t=1",
      "text": "16"
    },
    {
      "href": "https://thiruvachanam.in/ShowStatementsOfChapter.do?c=234&b=7&t=1",
      "text": "17"
    },
    {
      "href": "https://thiruvachanam.in/ShowStatementsOfChapter.do?c=235&b=7&t=1",
      "text": "18"
    },
    {
      "href": "https://thiruvachanam.in/ShowStatementsOfChapter.do?c=236&b=7&t=1",
      "text": "19"
    },
    {
      "href": "https://thiruvachanam.in/ShowStatementsOfChapter.do?c=237&b=7&t=1",
      "text": "20"
    },
    {
      "href": "https://thiruvachanam.in/ShowStatementsOfChapter.do?c=238&b=7&t=1",
      "text": "21"
    }
  ]
}